week1/JOOSANG/Joo_week2.v
 module I2C_Master (
    input wire clk,
    input wire nrst,
    input wire s_bit,
    //input wire RW_SEL,
    //input wire ack,
    
    //input wire [6:0] Device_Addr,
    //input wire [7:0] Data_in,
    //output reg [7:0] Data_out,

    output reg SCL,
    //input wire SDA_in,
    output reg SDA_out,
    output reg [3:0] state    
);


//input initial
reg RW_SEL_reg;
reg ack_reg;

reg SDA_reg;
reg SCL_reg;

reg clr=0;

reg [7:0] Data_reg = 0;
reg [7:0] Device_Addr_reg = 0;

//state define
parameter IDLE    = 4'd0;
parameter START   = 4'd1;
parameter DEV_SEL = 4'd2;
parameter READ    = 4'd3;
parameter WRITE   = 4'd4;
parameter ACK     = 4'd5;
parameter REG_SEL = 4'd6;
parameter DATA    = 4'd7;
parameter NACK    = 4'd8;
parameter STOP    = 4'd9;


reg [3:0] next_state = IDLE;

always @(posedge clk, negedge nrst)
    if(!nrst) state <= IDLE;
    else state <= next_state;

//state machine    
always @* begin
    case (state)
        IDLE:  
            if(s_bit) next_state = START;
            else next_state = IDLE;

        START:  
            next_state = DEV_SEL;  

        DEV_SEL :
		if (count == 8'd22 ) next_state = READ;		
		else next_state = DEV_SEL;
			

        /*DEV_SEL:
            if(RW_SEL_reg) next_state = WRITE;
            else next_state = READ;*/

        WRITE:
            next_state = REG_SEL;

        READ:
            next_state = REG_SEL;

        REG_SEL: 
            next_state = DATA;

        DATA:
            next_state = ACK;

        ACK:
             next_state = DATA;

        NACK:
            next_state = STOP;

        STOP:
            next_state = IDLE;

        default 
            next_state = IDLE;
    endcase
end



always @(posedge clk) begin
case (state)
    IDLE :
    begin
        //Device_Addr_reg <= Device_Addr;
        SDA_out <= 1'b1;
        SCL <= 1'b1;
    end

    START :
    begin
        SDA_out <= 1'b0;   
    end

endcase
end




//precale
reg [1:0] counter = 0;

always @(posedge clk) begin

    if(counter==3) begin
        clr <= ~clr;
        count <= 0;
        end
    else counter <= counter+1;
       
end

always @(posedge clk) begin
    if(state==IDLE) SCL <= 1'b1;
    else SCL <= clr;
end



////////state임시로 count로 계산//////////
reg [7:0] count;

always @ (posedge clk) begin			
	if(!nrst) begin	// rst Active
		count <= 8'd31;
	end
	
	else begin
		if(count > 8'd0) count <= count - 8'd1;			
		else count <= 8'd31;					
	end
end
////////////////////////////////////////////////

endmodule

//////////////////////////////////////

week1/JOOSANG/Joo_week2_TB.v
/*
module I2C_Master (
    input wire clk,
    input wire nrst,
    input wire s_bit,
    input wire RW_SEL,
    input wire ack,
    
    input wire [6:0] Device_Addr,
    input wire [7:0] Data_in,
    output reg [7:0] Data_out,

    output reg SCL,
    input wire SDA_in,
    output reg SDA_out

);
*/

module I2C_Masert_tb;

reg clk, nrst, s_bit;
wire SCL, SDA_out;
wire [3:0] state;

I2C_Master u0(.clk(clk), .nrst(nrst), .s_bit(s_bit), .SCL(SCL), .SDA_out(SDA_out), .state(state));

initial begin
    clk = 1'b0;
    forever #5 clk = ~clk;
end

initial begin
    nrst = 1'b0;
    #2
    nrst = 1'b1;
    #500
    nrst = 1'b0;
end

initial begin
    s_bit = 1'b0;
    #30
    s_bit = 1'b1;
end

initial begin
    $dumpfile("I2C_Master_tb.vcd");
    $dumpvars;
    #500
    $finish;
end

endmodule

week1/JOOSANG/I2C_Master_tb.vcd
$date
	Mon Feb 20 20:27:16 2023
$end
$version
	Icarus Verilog
$end
$timescale
	1s
$end
$scope module I2C_Masert_tb $end
$var wire 4 ! state [3:0] $end
$var wire 1 " SDA_out $end
$var wire 1 # SCL $end
$var reg 1 $ clk $end
$var reg 1 % nrst $end
$var reg 1 & s_bit $end
$scope module u0 $end
$var wire 1 $ clk $end
$var wire 1 % nrst $end
$var wire 1 & s_bit $end
$var parameter 4 ' ACK $end
$var parameter 4 ( DATA $end
$var parameter 4 ) DEV_SEL $end
$var parameter 4 * IDLE $end
$var parameter 4 + NACK $end
$var parameter 4 , READ $end
$var parameter 4 - REG_SEL $end
$var parameter 4 . START $end
$var parameter 4 / STOP $end
$var parameter 4 0 WRITE $end
$var reg 8 1 Data_reg [7:0] $end
$var reg 8 2 Device_Addr_reg [7:0] $end
$var reg 1 # SCL $end
$var reg 1 " SDA_out $end
$var reg 1 3 clr $end
$var reg 8 4 count [7:0] $end
$var reg 2 5 counter [1:0] $end
$var reg 4 6 next_state [3:0] $end
$var reg 4 7 state [3:0] $end
$upscope $end
$upscope $end
$enddefinitions $end
$comment Show the parameter values. $end
$dumpall
b100 0
b1001 /
b1 .
b110 -
b11 ,
b1000 +
b0 *
b10 )
b111 (
b101 '
$end
#0
$dumpvars
b0 7
b0 6
b0 5
bx 4
03
b0 2
b0 1
0&
0%
0$
x#
x"
b0 !
$end
#2
1%
#5
1"
b1 5
1#
b11111 4
1$
#10
0$
#15
b11110 4
b10 5
1$
#20
0$
#25
b11 5
b11101 4
1$
#30
b1 6
0$
1&
#35
b11100 4
13
b1 !
b1 7
1$
#40
0$
#45
0"
03
b0 4
1$
#50
0$
#55
b10 6
b11111 4
0#
13
1$
#60
0$
#65
03
1#
b0 4
b10 !
b10 7
1$
#70
0$
#75
b11111 4
0#
13
1$
#80
0$
#85
03
1#
b0 4
1$
#90
0$
#95
b11111 4
0#
13
1$
#100
0$
#105
03
1#
b0 4
1$
#110
0$
#115
b11111 4
0#
13
1$
#120
0$
#125
03
1#
b0 4
1$
#130
0$
#135
b11111 4
0#
13
1$
#140
0$
#145
03
1#
b0 4
1$
#150
0$
#155
b11111 4
0#
13
1$
#160
0$
#165
03
1#
b0 4
1$
#170
0$
#175
b11111 4
0#
13
1$
#180
0$
#185
03
1#
b0 4
1$
#190
0$
#195
b11111 4
0#
13
1$
#200
0$
#205
03
1#
b0 4
1$
#210
0$
#215
b11111 4
0#
13
1$
#220
0$
#225
03
1#
b0 4
1$
#230
0$
#235
b11111 4
0#
13
1$
#240
0$
#245
03
1#
b0 4
1$
#250
0$
#255
b11111 4
0#
13
1$
#260
0$
#265
03
1#
b0 4
1$
#270
0$
#275
b11111 4
0#
13
1$
#280
0$
#285
03
1#
b0 4
1$
#290
0$
#295
b11111 4
0#
13
1$
#300
0$
#305
03
1#
b0 4
1$
#310
0$
#315
b11111 4
0#
13
1$
#320
0$
#325
03
1#
b0 4
1$
#330
0$
#335
b11111 4
0#
13
1$
#340
0$
#345
03
1#
b0 4
1$
#350
0$
#355
b11111 4
0#
13
1$
#360
0$
#365
03
1#
b0 4
1$
#370
0$
#375
b11111 4
0#
13
1$
#380
0$
#385
03
1#
b0 4
1$
#390
0$
#395
b11111 4
0#
13
1$
#400
0$
#405
03
1#
b0 4
1$
#410
0$
#415
b11111 4
0#
13
1$
#420
0$
#425
03
1#
b0 4
1$
#430
0$
#435
b11111 4
0#
13
1$
#440
0$
#445
03
1#
b0 4
1$
#450
0$
#455
b11111 4
0#
13
1$
#460
0$
#465
03
1#
b0 4
1$
#470
0$
#475
b11111 4
0#
13
1$
#480
0$
#485
03
1#
b0 4
1$
#490
0$
#495
b11111 4
0#
13
1$
