week1/JOOSANG/main.v
module I2C_Master (

input	wire [7:0] Data_in,
input	wire [7:0] Reg_addr,
input	wire [6:0] Dev_addr,
input	wire	   clk,rst,RW_sel,

input	wire	 SDA_in,
output	reg	 SDA_out,
output	reg	 SCL_out

);


localparam STATE_IDLE 				= 4'd0;
localparam STATE_START 				= 4'd1;
localparam STATE_DEV_SEL 			= 4'd2;
localparam STATE_RW				= 4'd3;
localparam STATE_ACK_W			 	= 4'd4;

localparam STATE_REG_SEL	 		= 4'd5;
localparam STATE_ACK_REG		 	= 4'd6;

localparam STATE_READ 				= 4'd7;
localparam STATE_WRITE		 		= 4'd8;

localparam STATE_ACK_DATA			= 4'd9;
localparam STATE_NACK		 		= 4'd10;
localparam STATE_STOP				= 4'd11;

localparam STATE_RESTART			= 4'd12;

reg [3:0]  state = STATE_IDLE;
reg [3:0]  next_state = STATE_IDLE;

reg [3:0]  bit_count = 4'd0;
reg [3:0]  SCL_count = 4'd0;

wire	   SDA;
wire	   SCL;


reg [8:0] count;
reg [7:0] count1;

////////////////////////////////////////////////////////////////////////////////////

always @ (posedge clk) begin
	if(!rst)begin
		state <= STATE_IDLE;
	end

	else begin
		state <= next_state;
	end
end

////////////////////////////////////////////////////////////////////////////////////
always @ (*) begin
	case (state)
		STATE_IDLE : 				
		if (rst) begin
			next_state = STATE_START;
		end
		else begin
			next_state = STATE_IDLE;
		end

		STATE_START : 
		if (rst) begin
			next_state = STATE_DEV_SEL;
		end
		else  begin
			next_state = STATE_IDLE;
		end

		STATE_DEV_SEL :
		if (rst) begin
			next_state = STATE_RW;
		end

		else if (rst&(RW_sel)) begin
			next_state = STATE_RW;
		end

		else begin
			next_state = STATE_DEV_SEL;
            	end
		
		STATE_RW:
		if (rst) begin
			next_state = STATE_ACK_W;
		end
		else if (rst&(RW_sel)) begin
			next_state = STATE_ACK_W;
		end

		else begin
			next_state = STATE_IDLE;
            	end

		STATE_ACK_W :  				
		if (rst & (SDA_in == 0)) begin
			next_state = STATE_REG_SEL;
		end
		else if (rst&(RW_sel)) begin
			next_state = STATE_READ;
		end
		else begin
			next_state = STATE_IDLE;
		end

		STATE_REG_SEL : 				
		if (rst) begin
			next_state = STATE_ACK_REG;
		end
		else begin
			next_state = STATE_REG_SEL;
		end
		
		STATE_ACK_REG : 				
		if (rst & (SDA_in == 0)) begin
			if(RW_sel) begin
				next_state = STATE_RESTART;
			end
			else begin
				next_state = STATE_WRITE;
			end
		end
		else begin
			next_state = STATE_IDLE;
		end
		
		STATE_READ :  				
		if (rst) begin
			next_state = STATE_NACK;
		end
		else begin
			next_state = STATE_READ;
		end
		
		STATE_WRITE : 				
		if (rst) begin
			next_state = STATE_ACK_DATA;
		end
		else begin
			next_state = STATE_WRITE;
		end

		STATE_ACK_DATA : 				
		if (rst) begin
			next_state = STATE_STOP;
		end
		else begin
			next_state = STATE_IDLE;
		end
		
		STATE_NACK : 				
		if (rst) begin
			next_state = STATE_STOP;
		end
		else begin
			next_state = STATE_IDLE;
		end

		STATE_STOP : 		
		if (rst) begin
			next_state = STATE_IDLE;
		end
		else begin
			next_state = STATE_IDLE;
		end
		
		STATE_RESTART :
		if (rst) begin
			next_state = STATE_DEV_SEL;
		end
		else begin
			next_state = STATE_IDLE;
		end

		default next_state = STATE_IDLE;
	endcase
end

////////////////////////////////////////////////////////////////////////////////////
always @ (posedge clk) begin
	case (state)  
		STATE_IDLE : // Initialization
		begin
			SCL_out <= 1'b1;
			SDA_out <= 1'b1;
			bit_count <= 4'd0;
			SCL_count <= 4'd0;
			count1<= 8'd0;
			count<= 0;
		end
		
		STATE_START : // Write Start bit(0) on SDA (From Master to Slave)
		begin
			SDA_out <= 1'b0;
			bit_count <= 4'd7;
		end
		
		STATE_DEV_SEL : // Write Device Address [6:0] on SDA (From Master to Slave)
		begin
			if(bit_count) begin
				if(Dev_addr[bit_count - 4'd1]) begin
					SDA_out <= 1'b1;
				end
				else begin
					SDA_out <= 1'b0;
				end
			end
			bit_count = bit_count - 4'd1;
		end

		STATE_RW :	//Write W bit on SDA (From Master to Slave)
		begin	
			if ((RW_sel==1)&(count==8'd12)) begin
				SDA_out <= 1'b1;
			end
			else begin
				SDA_out <= 1'b0;
			end
		end

		STATE_ACK_W :			//Read ARK bit (From Slave to Master)
		begin	
			SDA_out <= 1'b0;
			bit_count <= 4'd8;
		end
		
		STATE_REG_SEL : // Write Register Address [7:0] on SDA (From Master to Slave)
		begin
			if(bit_count) begin
				if(Reg_addr[bit_count - 4'd1]) begin
					SDA_out <= 1'b1;
				end
				else begin
					SDA_out <= 1'b0;
				end
			end
			bit_count = bit_count - 4'd1;
		end

		STATE_ACK_REG :			//Read ARK bit (From Slave to Master)
		begin	
			SDA_out <= 1'b0;
			if(RW_sel)begin
				bit_count <= 4'd0;
			end
			else begin
				bit_count <= 4'd8;
			end
		end
		
		STATE_WRITE : //Write Data [7:0] on SDA (From Master to Slave)
		begin
			if(bit_count) begin
				if(Data_in[bit_count - 4'd1]) begin
					SDA_out <= 1'b1;
				end
				else begin
					SDA_out <= 1'b0;
				end
			end
			bit_count <= bit_count - 4'd1;
		end

		STATE_READ : //Read Data [7:0] on SDA (From Slave to Master)
		begin
			SDA_out <= 1'b0;
			bit_count <= bit_count - 4'd1;
		end

		STATE_ACK_DATA : 	//Read ARK bit (From Slave to Master)
		begin
			SDA_out <= 1'b0;
		end

		STATE_NACK : 		//Read NACK bit (From Slave to Master)
		begin
			SDA_out <= 1'b1;
		end

		STATE_STOP : //Write STOP bit on SDA (From Master to Slave)
		begin
			SDA_out <= 1'b1;
		end
		
		STATE_RESTART : 
		begin
			SDA_out <= 1'b0;
			bit_count <= 4'd7;
		end

	endcase
end

////////////////////////////////////////////////////////////////////////////////////

always @ (posedge clk) begin			
	if(!rst) begin
		count <= 8'd0;
	end
	
	else begin
		count <= count + 8'd1;

	end
end

////////////////////////////////////////////////////////////////////////////////////
always @ (posedge clk) begin
	if ( state >= STATE_START ) begin
		SCL_count <= SCL_count + 4'd1;
		if (SCL_count == 3) begin
       			 SCL_count <= 4'd0;
       			 SCL_out <= !SCL_out;
    		end
	end
end
////////////////////////////////////////////////////////////////////////////////////
always @ (posedge clk) begin
	count1 <= count1 + 8'd1;
	if ( count1 == 7) begin
	count1 <= 8'd0;
	bit_count <= bit_count + 4'd1;
	end
end

////////////////////////////////////////////////////////////////////////////////////
assign SDA = SDA_in + SDA_out;
assign SCL = SCL_out;
 	
////////////////////////////////////////////////////////////////////////////////////

endmodule

week1/JOOSANG/main_tb.v
module I2C_Master_TB;

reg [7:0] Data_in;
reg [7:0] Reg_addr;
reg [6:0] Dev_addr;
reg	   clk,rst,RW_sel;

reg	 SDA_in;
wire	 SDA_out;
wire	 SCL_out;

I2C_Master u0 (.Data_in(Data_in), .Reg_addr(Reg_addr), .Dev_addr(Dev_addr), .clk(clk), .rst(rst), .RW_sel(RW_sel), .SDA_in(SDA_in), .SDA_out(SDA_out), .SCL_out(SCL_out));

initial begin
	clk = 1'b0;
	forever #1 clk = ~clk;
end

initial begin
rst = 1'b0;
#9
rst = 1'b1;
end

initial begin
Dev_addr <= 7'b1010101;
RW_sel <= 1'b1;
Data_in <=  8'b01010101;
SDA_in <= 1'b0;
Reg_addr <= 8'b11010101;
end

initial begin
    $dumpfile("main.vcd");
    $dumpvars;
    #1000
    $finish;
end

endmodule

week1/JOOSANG/main.vcd
$date
	Tue Feb 21 19:12:11 2023
$end
$version
	Icarus Verilog
$end
$timescale
	1s
$end
$scope module I2C_Master_TB $end
$var wire 1 ! SDA_out $end
$var wire 1 " SCL_out $end
$var reg 8 # Data_in [7:0] $end
$var reg 7 $ Dev_addr [6:0] $end
$var reg 1 % RW_sel $end
$var reg 8 & Reg_addr [7:0] $end
$var reg 1 ' SDA_in $end
$var reg 1 ( clk $end
$var reg 1 ) rst $end
$scope module u0 $end
$var wire 8 * Data_in [7:0] $end
$var wire 7 + Dev_addr [6:0] $end
$var wire 1 % RW_sel $end
$var wire 8 , Reg_addr [7:0] $end
$var wire 1 - SCL $end
$var wire 1 ' SDA_in $end
$var wire 1 ( clk $end
$var wire 1 ) rst $end
$var wire 1 . SDA $end
$var parameter 4 / STATE_ACK_DATA $end
$var parameter 4 0 STATE_ACK_REG $end
$var parameter 4 1 STATE_ACK_W $end
$var parameter 4 2 STATE_DEV_SEL $end
$var parameter 4 3 STATE_IDLE $end
$var parameter 4 4 STATE_NACK $end
$var parameter 4 5 STATE_READ $end
$var parameter 4 6 STATE_REG_SEL $end
$var parameter 4 7 STATE_RESTART $end
$var parameter 4 8 STATE_RW $end
$var parameter 4 9 STATE_START $end
$var parameter 4 : STATE_STOP $end
$var parameter 4 ; STATE_WRITE $end
$var reg 4 < SCL_count [3:0] $end
$var reg 1 " SCL_out $end
$var reg 1 ! SDA_out $end
$var reg 4 = bit_count [3:0] $end
$var reg 9 > count [8:0] $end
$var reg 8 ? count1 [7:0] $end
$var reg 4 @ next_state [3:0] $end
$var reg 4 A state [3:0] $end
$upscope $end
$upscope $end
$enddefinitions $end
$comment Show the parameter values. $end
$dumpall
b1000 ;
b1011 :
b1 9
b11 8
b1100 7
b101 6
b111 5
b1010 4
b0 3
b10 2
b100 1
b110 0
b1001 /
$end
#0
$dumpvars
b0 A
b0 @
bx ?
bx >
b0 =
b0 <
x.
x-
b11010101 ,
b1010101 +
b1010101 *
0)
0(
0'
b11010101 &
1%
b1010101 $
b1010101 #
x"
x!
$end
#1
b0 ?
1.
1!
1-
1"
b0 >
1(
#2
0(
#3
b1 ?
1(
#4
0(
#5
b0 ?
1(
#6
0(
#7
b1 ?
1(
#8
0(
#9
b1 A
b0 >
b0 ?
b10 @
1(
1)
#10
0(
#11
b11 @
b1 ?
b1 <
b1 >
b111 =
0.
0!
b10 A
1(
#12
0(
#13
b100 @
b11 A
1.
1!
b10 >
b10 <
b10 ?
b110 =
1(
#14
0(
#15
b101 @
b11 ?
b11 <
b11 >
0.
0!
b100 A
1(
#16
0(
#17
b110 @
b101 A
b1000 =
b100 >
0-
0"
b0 <
b100 ?
1(
#18
0(
#19
b1100 @
b101 ?
b1 <
b101 >
1.
1!
b110 A
b111 =
1(
#20
0(
#21
b10 @
b1100 A
b0 =
0.
0!
b110 >
b10 <
b110 ?
1(
#22
0(
#23
b11 @
b111 ?
b11 <
b111 >
b111 =
b10 A
1(
#24
0(
#25
b100 @
b11 A
1.
1!
b1000 >
1-
1"
b0 <
b0 ?
b1000 =
1(
#26
0(
#27
b101 @
b1 ?
b1 <
b1001 >
0.
0!
b100 A
1(
#28
0(
#29
b110 @
b101 A
b1010 >
b10 <
b10 ?
1(
#30
0(
#31
b1100 @
b11 ?
b11 <
b1011 >
1.
1!
b110 A
b111 =
1(
#32
0(
#33
b10 @
b1100 A
b0 =
0.
0!
b1100 >
0-
0"
b0 <
b100 ?
1(
#34
0(
#35
b11 @
b101 ?
b1 <
b1101 >
b111 =
b10 A
1(
#36
0(
#37
b100 @
b11 A
1.
1!
b1110 >
b10 <
b110 ?
b110 =
1(
#38
0(
#39
b101 @
b111 ?
b11 <
b1111 >
0.
0!
b100 A
1(
#40
0(
#41
b110 @
b101 A
b10000 >
1-
1"
b0 <
b1000 =
b0 ?
1(
#42
0(
#43
b1100 @
b1 ?
b1 <
b10001 >
1.
1!
b110 A
b111 =
1(
#44
0(
#45
b10 @
b1100 A
b0 =
0.
0!
b10010 >
b10 <
b10 ?
1(
#46
0(
#47
b11 @
b11 ?
b11 <
b10011 >
b111 =
b10 A
1(
#48
0(
#49
b100 @
b11 A
1.
1!
b10100 >
0-
0"
b0 <
b100 ?
b110 =
1(
#50
0(
#51
b101 @
b101 ?
b1 <
b10101 >
0.
0!
b100 A
1(
#52
0(
#53
b110 @
b101 A
b1000 =
b10110 >
b10 <
b110 ?
1(
#54
0(
#55
b1100 @
b111 ?
b11 <
b10111 >
1.
1!
b110 A
b111 =
1(
#56
0(
#57
b10 @
b1100 A
0.
0!
b11000 >
1-
1"
b0 <
b0 =
b0 ?
1(
#58
0(
#59
b11 @
b1 ?
b1 <
b11001 >
b111 =
b10 A
1(
#60
0(
#61
b100 @
b11 A
1.
1!
b11010 >
b10 <
b10 ?
b110 =
1(
#62
0(
#63
b101 @
b11 ?
b11 <
b11011 >
0.
0!
b100 A
1(
#64
0(
#65
b110 @
b101 A
b1000 =
b11100 >
0-
0"
b0 <
b100 ?
1(
#66
0(
#67
b1100 @
b101 ?
b1 <
b11101 >
1.
1!
b110 A
b111 =
1(
#68
0(
#69
b10 @
b1100 A
b0 =
0.
0!
b11110 >
b10 <
b110 ?
1(
#70
0(
#71
b11 @
b111 ?
b11 <
b11111 >
b111 =
b10 A
1(
#72
0(
#73
b100 @
b11 A
1.
1!
b100000 >
1-
1"
b0 <
b0 ?
b1000 =
1(
#74
0(
#75
b101 @
b1 ?
b1 <
b100001 >
0.
0!
b100 A
1(
#76
0(
#77
b110 @
b101 A
b100010 >
b10 <
b10 ?
1(
#78
0(
#79
b1100 @
b11 ?
b11 <
b100011 >
1.
1!
b110 A
b111 =
1(
#80
0(
#81
b10 @
b1100 A
b0 =
0.
0!
b100100 >
0-
0"
b0 <
b100 ?
1(
#82
0(
#83
b11 @
b101 ?
b1 <
b100101 >
b111 =
b10 A
1(
#84
0(
#85
b100 @
b11 A
1.
1!
b100110 >
b10 <
b110 ?
b110 =
1(
#86
0(
#87
b101 @
b111 ?
b11 <
b100111 >
0.
0!
b100 A
1(
#88
0(
#89
b110 @
b101 A
b101000 >
1-
1"
b0 <
b1000 =
b0 ?
1(
#90
0(
#91
b1100 @
b1 ?
b1 <
b101001 >
1.
1!
b110 A
b111 =
1(
#92
0(
#93
b10 @
b1100 A
b0 =
0.
0!
b101010 >
b10 <
b10 ?
1(
#94
0(
#95
b11 @
b11 ?
b11 <
b101011 >
b111 =
b10 A
1(
#96
0(
#97
b100 @
b11 A
1.
1!
b101100 >
0-
0"
b0 <
b100 ?
b110 =
1(
#98
0(
#99
b101 @
b101 ?
b1 <
b101101 >
0.
0!
b100 A
1(
#100
0(
#101
b110 @
b101 A
b1000 =
b101110 >
b10 <
b110 ?
1(
#102
0(
#103
b1100 @
b111 ?
b11 <
b101111 >
1.
1!
b110 A
b111 =
1(
#104
0(
#105
b10 @
b1100 A
0.
0!
b110000 >
1-
1"
b0 <
b0 =
b0 ?
1(
#106
0(
#107
b11 @
b1 ?
b1 <
b110001 >
b111 =
b10 A
1(
#108
0(
#109
b100 @
b11 A
1.
1!
b110010 >
b10 <
b10 ?
b110 =
1(
#110
0(
#111
b101 @
b11 ?
b11 <
b110011 >
0.
0!
b100 A
1(
#112
0(
#113
b110 @
b101 A
b1000 =
b110100 >
0-
0"
b0 <
b100 ?
1(
#114
0(
#115
b1100 @
b101 ?
b1 <
b110101 >
1.
1!
b110 A
b111 =
1(
#116
0(
#117
b10 @
b1100 A
b0 =
0.
0!
b110110 >
b10 <
b110 ?
1(
#118
0(
#119
b11 @
b111 ?
b11 <
b110111 >
b111 =
b10 A
1(
#120
0(
#121
b100 @
b11 A
1.
1!
b111000 >
1-
1"
b0 <
b0 ?
b1000 =
1(
#122
0(
#123
b101 @
b1 ?
b1 <
b111001 >
0.
0!
b100 A
1(
#124
0(
#125
b110 @
b101 A
b111010 >
b10 <
b10 ?
1(
#126
0(
#127
b1100 @
b11 ?
b11 <
b111011 >
1.
1!
b110 A
b111 =
1(
#128
0(
#129
b10 @
b1100 A
b0 =
0.
0!
b111100 >
0-
0"
b0 <
b100 ?
1(
#130
0(
#131
b11 @
b101 ?
b1 <
b111101 >
b111 =
b10 A
1(
#132
0(
#133
b100 @
b11 A
1.
1!
b111110 >
b10 <
b110 ?
b110 =
1(
#134
0(
#135
b101 @
b111 ?
b11 <
b111111 >
0.
0!
b100 A
1(
#136
0(
#137
b110 @
b101 A
b1000000 >
1-
1"
b0 <
b1000 =
b0 ?
1(
#138
0(
#139
b1100 @
b1 ?
b1 <
b1000001 >
1.
1!
b110 A
b111 =
1(
#140
0(
#141
b10 @
b1100 A
b0 =
0.
0!
b1000010 >
b10 <
b10 ?
1(
#142
0(
#143
b11 @
b11 ?
b11 <
b1000011 >
b111 =
b10 A
1(
#144
0(
#145
b100 @
b11 A
1.
1!
b1000100 >
0-
0"
b0 <
b100 ?
b110 =
1(
#146
0(
#147
b101 @
b101 ?
b1 <
b1000101 >
0.
0!
b100 A
1(
#148
0(
#149
b110 @
b101 A
b1000 =
b1000110 >
b10 <
b110 ?
1(
#150
0(
#151
b1100 @
b111 ?
b11 <
b1000111 >
1.
1!
b110 A
b111 =
1(
#152
0(
#153
b10 @
b1100 A
0.
0!
b1001000 >
1-
1"
b0 <
b0 =
b0 ?
1(
#154
0(
#155
b11 @
b1 ?
b1 <
b1001001 >
b111 =
b10 A
1(
#156
0(
#157
b100 @
b11 A
1.
1!
b1001010 >
b10 <
b10 ?
b110 =
1(
#158
0(
#159
b101 @
b11 ?
b11 <
b1001011 >
0.
0!
b100 A
1(
#160
0(
#161
b110 @
b101 A
b1000 =
b1001100 >
0-
0"
b0 <
b100 ?
1(
#162
0(
#163
b1100 @
b101 ?
b1 <
b1001101 >
1.
1!
b110 A
b111 =
1(
#164
0(
#165
b10 @
b1100 A
b0 =
0.
0!
b1001110 >
b10 <
b110 ?
1(
#166
0(
#167
b11 @
b111 ?
b11 <
b1001111 >
b111 =
b10 A
1(
#168
0(
#169
b100 @
b11 A
1.
1!
b1010000 >
1-
1"
b0 <
b0 ?
b1000 =
1(
#170
0(
#171
b101 @
b1 ?
b1 <
b1010001 >
0.
0!
b100 A
1(
#172
0(
#173
b110 @
b101 A
b1010010 >
b10 <
b10 ?
1(
#174
0(
#175
b1100 @
b11 ?
b11 <
b1010011 >
1.
1!
b110 A
b111 =
1(
#176
0(
#177
b10 @
b1100 A
b0 =
0.
0!
b1010100 >
0-
0"
b0 <
b100 ?
1(
#178
0(
#179
b11 @
b101 ?
b1 <
b1010101 >
b111 =
b10 A
1(
#180
0(
#181
b100 @
b11 A
1.
1!
b1010110 >
b10 <
b110 ?
b110 =
1(
#182
0(
#183
b101 @
b111 ?
b11 <
b1010111 >
0.
0!
b100 A
1(
#184
0(
#185
b110 @
b101 A
b1011000 >
1-
1"
b0 <
b1000 =
b0 ?
1(
#186
0(
#187
b1100 @
b1 ?
b1 <
b1011001 >
1.
1!
b110 A
b111 =
1(
#188
0(
#189
b10 @
b1100 A
b0 =
0.
0!
b1011010 >
b10 <
b10 ?
1(
#190
0(
#191
b11 @
b11 ?
b11 <
b1011011 >
b111 =
b10 A
1(
#192
0(
#193
b100 @
b11 A
1.
1!
b1011100 >
0-
0"
b0 <
b100 ?
b110 =
1(
#194
0(
#195
b101 @
b101 ?
b1 <
b1011101 >
0.
0!
b100 A
1(
#196
0(
#197
b110 @
b101 A
b1000 =
b1011110 >
b10 <
b110 ?
1(
#198
0(
#199
b1100 @
b111 ?
b11 <
b1011111 >
1.
1!
b110 A
b111 =
1(
#200
0(
#201
b10 @
b1100 A
0.
0!
b1100000 >
1-
1"
b0 <
b0 =
b0 ?
1(
#202
0(
#203
b11 @
b1 ?
b1 <
b1100001 >
b111 =
b10 A
1(
#204
0(
#205
b100 @
b11 A
1.
1!
b1100010 >
b10 <
b10 ?
b110 =
1(
#206
0(
#207
b101 @
b11 ?
b11 <
b1100011 >
0.
0!
b100 A
1(
#208
0(
#209
b110 @
b101 A
b1000 =
b1100100 >
0-
0"
b0 <
b100 ?
1(
#210
0(
#211
b1100 @
b101 ?
b1 <
b1100101 >
1.
1!
b110 A
b111 =
1(
#212
0(
#213
b10 @
b1100 A
b0 =
0.
0!
b1100110 >
b10 <
b110 ?
1(
#214
0(
#215
b11 @
b111 ?
b11 <
b1100111 >
b111 =
b10 A
1(
#216
0(
#217
b100 @
b11 A
1.
1!
b1101000 >
1-
1"
b0 <
b0 ?
b1000 =
1(
#218
0(
#219
b101 @
b1 ?
b1 <
b1101001 >
0.
0!
b100 A
1(
#220
0(
#221
b110 @
b101 A
b1101010 >
b10 <
b10 ?
1(
#222
0(
#223
b1100 @
b11 ?
b11 <
b1101011 >
1.
1!
b110 A
b111 =
1(
#224
0(
#225
b10 @
b1100 A
b0 =
0.
0!
b1101100 >
0-
0"
b0 <
b100 ?
1(
#226
0(
#227
b11 @
b101 ?
b1 <
b1101101 >
b111 =
b10 A
1(
#228
0(
#229
b100 @
b11 A
1.
1!
b1101110 >
b10 <
b110 ?
b110 =
1(
#230
0(
#231
b101 @
b111 ?
b11 <
b1101111 >
0.
0!
b100 A
1(
#232
0(
#233
b110 @
b101 A
b1110000 >
1-
1"
b0 <
b1000 =
b0 ?
1(
#234
0(
#235
b1100 @
b1 ?
b1 <
b1110001 >
1.
1!
b110 A
b111 =
1(
#236
0(
#237
b10 @
b1100 A
b0 =
0.
0!
b1110010 >
b10 <
b10 ?
1(
#238
0(
#239
b11 @
b11 ?
b11 <
b1110011 >
b111 =
b10 A
1(
#240
0(
#241
b100 @
b11 A
1.
1!
b1110100 >
0-
0"
b0 <
b100 ?
b110 =
1(
#242
0(
#243
b101 @
b101 ?
b1 <
b1110101 >
0.
0!
b100 A
1(
#244
0(
#245
b110 @
b101 A
b1000 =
b1110110 >
b10 <
b110 ?
1(
#246
0(
#247
b1100 @
b111 ?
b11 <
b1110111 >
1.
1!
b110 A
b111 =
1(
#248
0(
#249
b10 @
b1100 A
0.
0!
b1111000 >
1-
1"
b0 <
b0 =
b0 ?
1(
#250
0(
#251
b11 @
b1 ?
b1 <
b1111001 >
b111 =
b10 A
1(
#252
0(
#253
b100 @
b11 A
1.
1!
b1111010 >
b10 <
b10 ?
b110 =
1(
#254
0(
#255
b101 @
b11 ?
b11 <
b1111011 >
0.
0!
b100 A
1(
#256
0(
#257
b110 @
b101 A
b1000 =
b1111100 >
0-
0"
b0 <
b100 ?
1(
#258
0(
#259
b1100 @
b101 ?
b1 <
b1111101 >
1.
1!
b110 A
b111 =
1(
#260
0(
#261
b10 @
b1100 A
b0 =
0.
0!
b1111110 >
b10 <
b110 ?
1(
#262
0(
#263
b11 @
b111 ?
b11 <
b1111111 >
b111 =
b10 A
1(
#264
0(
#265
b100 @
b11 A
1.
1!
b10000000 >
1-
1"
b0 <
b0 ?
b1000 =
1(
#266
0(
#267
b101 @
b1 ?
b1 <
b10000001 >
0.
0!
b100 A
1(
#268
0(
#269
b110 @
b101 A
b10000010 >
b10 <
b10 ?
1(
#270
0(
#271
b1100 @
b11 ?
b11 <
b10000011 >
1.
1!
b110 A
b111 =
1(
#272
0(
#273
b10 @
b1100 A
b0 =
0.
0!
b10000100 >
0-
0"
b0 <
b100 ?
1(
#274
0(
#275
b11 @
b101 ?
b1 <
b10000101 >
b111 =
b10 A
1(
#276
0(
#277
b100 @
b11 A
1.
1!
b10000110 >
b10 <
b110 ?
b110 =
1(
#278
0(
#279
b101 @
b111 ?
b11 <
b10000111 >
0.
0!
b100 A
1(
#280
0(
#281
b110 @
b101 A
b10001000 >
1-
1"
b0 <
b1000 =
b0 ?
1(
#282
0(
#283
b1100 @
b1 ?
b1 <
b10001001 >
1.
1!
b110 A
b111 =
1(
#284
0(
#285
b10 @
b1100 A
b0 =
0.
0!
b10001010 >
b10 <
b10 ?
1(
#286
0(
#287
b11 @
b11 ?
b11 <
b10001011 >
b111 =
b10 A
1(
#288
0(
#289
b100 @
b11 A
1.
1!
b10001100 >
0-
0"
b0 <
b100 ?
b110 =
1(
#290
0(
#291
b101 @
b101 ?
b1 <
b10001101 >
0.
0!
b100 A
1(
#292
0(
#293
b110 @
b101 A
b1000 =
b10001110 >
b10 <
b110 ?
1(
#294
0(
#295
b1100 @
b111 ?
b11 <
b10001111 >
1.
1!
b110 A
b111 =
1(
#296
0(
#297
b10 @
b1100 A
0.
0!
b10010000 >
1-
1"
b0 <
b0 =
b0 ?
1(
#298
0(
#299
b11 @
b1 ?
b1 <
b10010001 >
b111 =
b10 A
1(
#300
0(
#301
b100 @
b11 A
1.
1!
b10010010 >
b10 <
b10 ?
b110 =
1(
#302
0(
#303
b101 @
b11 ?
b11 <
b10010011 >
0.
0!
b100 A
1(
#304
0(
#305
b110 @
b101 A
b1000 =
b10010100 >
0-
0"
b0 <
b100 ?
1(
#306
0(
#307
b1100 @
b101 ?
b1 <
b10010101 >
1.
1!
b110 A
b111 =
1(
#308
0(
#309
b10 @
b1100 A
b0 =
0.
0!
b10010110 >
b10 <
b110 ?
1(
#310
0(
#311
b11 @
b111 ?
b11 <
b10010111 >
b111 =
b10 A
1(
#312
0(
#313
b100 @
b11 A
1.
1!
b10011000 >
1-
1"
b0 <
b0 ?
b1000 =
1(
#314
0(
#315
b101 @
b1 ?
b1 <
b10011001 >
0.
0!
b100 A
1(
#316
0(
#317
b110 @
b101 A
b10011010 >
b10 <
b10 ?
1(
#318
0(
#319
b1100 @
b11 ?
b11 <
b10011011 >
1.
1!
b110 A
b111 =
1(
#320
0(
#321
b10 @
b1100 A
b0 =
0.
0!
b10011100 >
0-
0"
b0 <
b100 ?
1(
#322
0(
#323
b11 @
b101 ?
b1 <
b10011101 >
b111 =
b10 A
1(
#324
0(
#325
b100 @
b11 A
1.
1!
b10011110 >
b10 <
b110 ?
b110 =
1(
#326
0(
#327
b101 @
b111 ?
b11 <
b10011111 >
0.
0!
b100 A
1(
#328
0(
#329
b110 @
b101 A
b10100000 >
1-
1"
b0 <
b1000 =
b0 ?
1(
#330
0(
#331
b1100 @
b1 ?
b1 <
b10100001 >
1.
1!
b110 A
b111 =
1(
#332
0(
#333
b10 @
b1100 A
b0 =
0.
0!
b10100010 >
b10 <
b10 ?
1(
#334
0(
#335
b11 @
b11 ?
b11 <
b10100011 >
b111 =
b10 A
1(
#336
0(
#337
b100 @
b11 A
1.
1!
b10100100 >
0-
0"
b0 <
b100 ?
b110 =
1(
#338
0(
#339
b101 @
b101 ?
b1 <
b10100101 >
0.
0!
b100 A
1(
#340
0(
#341
b110 @
b101 A
b1000 =
b10100110 >
b10 <
b110 ?
1(
#342
0(
#343
b1100 @
b111 ?
b11 <
b10100111 >
1.
1!
b110 A
b111 =
1(
#344
0(
#345
b10 @
b1100 A
0.
0!
b10101000 >
1-
1"
b0 <
b0 =
b0 ?
1(
#346
0(
#347
b11 @
b1 ?
b1 <
b10101001 >
b111 =
b10 A
1(
#348
0(
#349
b100 @
b11 A
1.
1!
b10101010 >
b10 <
b10 ?
b110 =
1(
#350
0(
#351
b101 @
b11 ?
b11 <
b10101011 >
0.
0!
b100 A
1(
#352
0(
#353
b110 @
b101 A
b1000 =
b10101100 >
0-
0"
b0 <
b100 ?
1(
#354
0(
#355
b1100 @
b101 ?
b1 <
b10101101 >
1.
1!
b110 A
b111 =
1(
#356
0(
#357
b10 @
b1100 A
b0 =
0.
0!
b10101110 >
b10 <
b110 ?
1(
#358
0(
#359
b11 @
b111 ?
b11 <
b10101111 >
b111 =
b10 A
1(
#360
0(
#361
b100 @
b11 A
1.
1!
b10110000 >
1-
1"
b0 <
b0 ?
b1000 =
1(
#362
0(
#363
b101 @
b1 ?
b1 <
b10110001 >
0.
0!
b100 A
1(
#364
0(
#365
b110 @
b101 A
b10110010 >
b10 <
b10 ?
1(
#366
0(
#367
b1100 @
b11 ?
b11 <
b10110011 >
1.
1!
b110 A
b111 =
1(
#368
0(
#369
b10 @
b1100 A
b0 =
0.
0!
b10110100 >
0-
0"
b0 <
b100 ?
1(
#370
0(
#371
b11 @
b101 ?
b1 <
b10110101 >
b111 =
b10 A
1(
#372
0(
#373
b100 @
b11 A
1.
1!
b10110110 >
b10 <
b110 ?
b110 =
1(
#374
0(
#375
b101 @
b111 ?
b11 <
b10110111 >
0.
0!
b100 A
1(
#376
0(
#377
b110 @
b101 A
b10111000 >
1-
1"
b0 <
b1000 =
b0 ?
1(
#378
0(
#379
b1100 @
b1 ?
b1 <
b10111001 >
1.
1!
b110 A
b111 =
1(
#380
0(
#381
b10 @
b1100 A
b0 =
0.
0!
b10111010 >
b10 <
b10 ?
1(
#382
0(
#383
b11 @
b11 ?
b11 <
b10111011 >
b111 =
b10 A
1(
#384
0(
#385
b100 @
b11 A
1.
1!
b10111100 >
0-
0"
b0 <
b100 ?
b110 =
1(
#386
0(
#387
b101 @
b101 ?
b1 <
b10111101 >
0.
0!
b100 A
1(
#388
0(
#389
b110 @
b101 A
b1000 =
b10111110 >
b10 <
b110 ?
1(
#390
0(
#391
b1100 @
b111 ?
b11 <
b10111111 >
1.
1!
b110 A
b111 =
1(
#392
0(
#393
b10 @
b1100 A
0.
0!
b11000000 >
1-
1"
b0 <
b0 =
b0 ?
1(
#394
0(
#395
b11 @
b1 ?
b1 <
b11000001 >
b111 =
b10 A
1(
#396
0(
#397
b100 @
b11 A
1.
1!
b11000010 >
b10 <
b10 ?
b110 =
1(
#398
0(
#399
b101 @
b11 ?
b11 <
b11000011 >
0.
0!
b100 A
1(
#400
0(
#401
b110 @
b101 A
b1000 =
b11000100 >
0-
0"
b0 <
b100 ?
1(
#402
0(
#403
b1100 @
b101 ?
b1 <
b11000101 >
1.
1!
b110 A
b111 =
1(
#404
0(
#405
b10 @
b1100 A
b0 =
0.
0!
b11000110 >
b10 <
b110 ?
1(
#406
0(
#407
b11 @
b111 ?
b11 <
b11000111 >
b111 =
b10 A
1(
#408
0(
#409
b100 @
b11 A
1.
1!
b11001000 >
1-
1"
b0 <
b0 ?
b1000 =
1(
#410
0(
#411
b101 @
b1 ?
b1 <
b11001001 >
0.
0!
b100 A
1(
#412
0(
#413
b110 @
b101 A
b11001010 >
b10 <
b10 ?
1(
#414
0(
#415
b1100 @
b11 ?
b11 <
b11001011 >
1.
1!
b110 A
b111 =
1(
#416
0(
